cmake_pc_hooks/__init__.py
cmake_pc_hooks/_argparse.py
cmake_pc_hooks/_call_process.py
cmake_pc_hooks/_cmake.py
cmake_pc_hooks/_utils.py
cmake_pc_hooks/clang_format.py
cmake_pc_hooks/clang_tidy.py
cmake_pc_hooks/cppcheck.py
cmake_pc_hooks/cpplint.py
cmake_pc_hooks/include_what_you_use.py
cmake_pc_hooks/lizard.py
cmake_pre_commit_hooks-1.9.6.dist-info/LICENSE
cmake_pre_commit_hooks-1.9.6.dist-info/METADATA
cmake_pre_commit_hooks-1.9.6.dist-info/WHEEL
cmake_pre_commit_hooks-1.9.6.dist-info/entry_points.txt
cmake_pre_commit_hooks-1.9.6.dist-info/top_level.txt
cmake_pre_commit_hooks-1.9.6.dist-info/RECORD
