Metadata-Version: 2.1
Name: cmake_pre_commit_hooks
Version: 1.9.6
Summary: pre-commit hooks for CMake-based projects
Author-email: Damien Nguyen <ngn.damien@gmail.com>
License: Apache2
Project-URL: Homepage, https://github.com/Takishima/cmake-pre-commit-hooks
Project-URL: Pypi, https://pypi.org/project/cmake-pre-commit-hooks/
Project-URL: Repository, https://github.com/Takishima/cmake-pre-commit-hooks
Project-URL: Issues, https://github.com/Takishima/cmake-pre-commit-hooks/issues
Project-URL: Changelog, https://github.com/Takishima/cmake-pre-commit-hooks/blob/main/CHANGELOG.md
Classifier: License :: OSI Approved :: Apache Software License
Classifier: Programming Language :: Python :: 3
Classifier: Programming Language :: Python :: 3 :: Only
Classifier: Programming Language :: Python :: 3.8
Classifier: Programming Language :: Python :: 3.9
Classifier: Programming Language :: Python :: 3.10
Classifier: Programming Language :: Python :: 3.11
Classifier: Programming Language :: Python :: 3.12
Requires-Python: >=3.8
License-File: LICENSE
Requires-Dist: toml
Requires-Dist: CLinters >=1.3.0
Requires-Dist: fasteners
Requires-Dist: filelock
Requires-Dist: attrs >=23
Requires-Dist: lizard
Provides-Extra: clang-format
Requires-Dist: clang-format ; extra == 'clang-format'
Provides-Extra: clang-tidy
Requires-Dist: clang-tidy ; extra == 'clang-tidy'
Provides-Extra: lizard
Requires-Dist: lizard ; extra == 'lizard'
Provides-Extra: test
Requires-Dist: pytest ; extra == 'test'
Requires-Dist: pytest-cov ; extra == 'test'
Requires-Dist: pytest-mock ; extra == 'test'
Requires-Dist: mock ; extra == 'test'
